football_game/__init__.py
football_game/__main__.py
football_game/schemas/__init__.py
football_game/schemas/_player.py
football_game/schemas/_team.py
football_game/schemas/_trainer.py
football_game/schemas/players.csv
football_game/schemas/teams.csv
football_game/schemas/trainers.csv
football_game-0.1.6.dist-info/METADATA
football_game-0.1.6.dist-info/WHEEL
football_game-0.1.6.dist-info/RECORD
