Metadata-Version: 2.1
Name: football-game
Version: 0.1.6
Summary: package python football game
Author: Julio Martinez del Pino
Author-email: juliomdp92@gmail.com
Requires-Python: >=3.9,<3.13
Classifier: Programming Language :: Python :: 3
Classifier: Programming Language :: Python :: 3.9
Classifier: Programming Language :: Python :: 3.10
Classifier: Programming Language :: Python :: 3.11
Classifier: Programming Language :: Python :: 3.12
Requires-Dist: pandas (>=2.2.0,<3.0.0)
Requires-Dist: psycopg2-binary (==2.9.*)
Requires-Dist: python-decouple (==3.8)
Requires-Dist: sqlmodel (==0.0.*)
